pbjam/DR.py
pbjam/IO.py
pbjam/__init__.py
pbjam/background.py
pbjam/core.py
pbjam/distributions.py
pbjam/jar.py
pbjam/l1models.py
pbjam/l20models.py
pbjam/modeID.py
pbjam/peakbagging.py
pbjam/plotting.py
pbjam/samplers.py
pbjam/validation.py
pbjam/version.py
pbjam/data/parameters.json
pbjam/data/prior_data.csv
pbjam-2.0.4.dist-info/LICENSE
pbjam-2.0.4.dist-info/METADATA
pbjam-2.0.4.dist-info/WHEEL
pbjam-2.0.4.dist-info/top_level.txt
pbjam-2.0.4.dist-info/RECORD
