Metadata-Version: 2.2
Name: pbjam
Version: 2.0.4
Summary: A package for peakbagging solar-like oscillators.
Author-email: Martin Nielsen <m.b.nielsen.1@bham.ac.uk>, Guy Davies <g.r.davies@bham.ac.uk>, Joel Ong <joelong@hawaii.edu>
Maintainer-email: Martin Nielsen <m.b.nielsen.1@bham.ac.uk>
License: MIT License
Project-URL: Homepage, https://pbjam.readthedocs.io/
Project-URL: Issues, https://github.com/grd349/PBjam/issues
Project-URL: Documentation, https://pbjam.readthedocs.io/
Project-URL: Repository, https://github.com/grd349/PBjam
Keywords: asteroseismology,astronomy,stars,solar-like
Classifier: Development Status :: 5 - Production/Stable
Classifier: Programming Language :: Python :: 3.10
Requires-Python: >=3.10
License-File: LICENSE
Requires-Dist: numpy>=2.2.4
Requires-Dist: scipy>=1.15.2
Requires-Dist: statsmodels>=0.14.4
Requires-Dist: matplotlib>=3.10
Requires-Dist: pandas>=2.2.3
Requires-Dist: lightkurve>=2.5.0
Requires-Dist: astropy>=6.1.7
Requires-Dist: corner>=2.2.3
Requires-Dist: dynesty>=2.1.5
Requires-Dist: jax>=0.5.2
Requires-Dist: jaxlib>=0.5.1
Requires-Dist: emcee>=3.1.6
Requires-Dist: tqdm>=4.67.1
Provides-Extra: test
Requires-Dist: pytest; extra == "test"
Provides-Extra: docs
Requires-Dist: sphinx; extra == "docs"
Requires-Dist: nbsphinx; extra == "docs"
Requires-Dist: ipykernel; extra == "docs"
